maby/__init__.py
maby/data.py
maby/downloads.yaml
maby/evaluate.py
maby/logging.conf
maby/model.py
maby/preprocessing.py
maby/train.py
maby/visualize.py
maby-0.1.dist-info/LICENSE.md
maby-0.1.dist-info/METADATA
maby-0.1.dist-info/WHEEL
maby-0.1.dist-info/entry_points.txt
maby-0.1.dist-info/top_level.txt
maby-0.1.dist-info/RECORD
