Metadata-Version: 2.1
Name: maby
Version: 0.1
Summary: U-Net for sub-cellular segmentation from Bright field
Home-page: 
Author: Diane Adjavon
Author-email: diane.adjavon@ed.ac.uk
License: MIT
Requires-Python: >=3.7
License-File: LICENSE.md
Requires-Dist: numpy
Requires-Dist: torch
Requires-Dist: matplotlib
Requires-Dist: seaborn
Requires-Dist: scikit-learn
Requires-Dist: scikit-image
Requires-Dist: pyyaml
